{
	"meta": {
		"image": "scene5.png",
		"size": {"w":1676,"h":1510},
		"scale": "1"
	},
	"frames": {
		"drilling_iceberg2.png":
		{
            "frame": {"x":0,"y":0,"w":1028,"h":764},
            "rotated": false,
            "trimmed": false,
            "spriteSourceSize": {"x":0,"y":0,"w":1028,"h":764},
            "sourceSize": {"w":1028,"h":764}
		},
		"drilling_iceberg1.png":
		{
            "frame": {"x":1028,"y":0,"w":648,"h":760},
            "rotated": false,
            "trimmed": false,
            "spriteSourceSize": {"x":0,"y":0,"w":648,"h":760},
            "sourceSize": {"w":648,"h":760}
		},
		"fpso_01.png":
		{
            "frame": {"x":0,"y":764,"w":217,"h":373},
            "rotated": false,
            "trimmed": false,
            "spriteSourceSize": {"x":0,"y":0,"w":217,"h":373},
            "sourceSize": {"w":217,"h":373}
		},
		"fpso_02.png":
		{
            "frame": {"x":217,"y":764,"w":338,"h":373},
            "rotated": false,
            "trimmed": false,
            "spriteSourceSize": {"x":0,"y":0,"w":338,"h":373},
            "sourceSize": {"w":338,"h":373}
		},
		"fpso_03.png":
		{
            "frame": {"x":555,"y":764,"w":364,"h":373},
            "rotated": false,
            "trimmed": false,
            "spriteSourceSize": {"x":0,"y":0,"w":364,"h":373},
            "sourceSize": {"w":364,"h":373}
		},
		"fpso_04.png":
		{
            "frame": {"x":919,"y":764,"w":582,"h":373},
            "rotated": false,
            "trimmed": false,
            "spriteSourceSize": {"x":0,"y":0,"w":582,"h":373},
            "sourceSize": {"w":582,"h":373}
		},
		"fpso_05.png":
		{
            "frame": {"x":0,"y":1137,"w":549,"h":373},
            "rotated": false,
            "trimmed": false,
            "spriteSourceSize": {"x":0,"y":0,"w":549,"h":373},
            "sourceSize": {"w":549,"h":373}
		},
		"s5_1px.png":
		{
            "frame": {"x":1028,"y":760,"w":1,"h":1},
            "rotated": false,
            "trimmed": false,
            "spriteSourceSize": {"x":0,"y":0,"w":1,"h":1},
            "sourceSize": {"w":1,"h":1}
		}
	}
}